jsonify_html/__init__.py
jsonify_html/command_manager.py
jsonify_html/exceptions.py
jsonify_html/template_manager.py
jsonify_html/utils.py
jsonify_html/cmd/__init__.py
jsonify_html/cmd/buildin_cmd.py
jsonify_html/parser/__init__.py
jsonify_html/parser/constant.py
jsonify_html/parser/selector.py
jsonify_html/parser/template.py
jsonify_html-1.0.8.dist-info/LICENSE
jsonify_html-1.0.8.dist-info/METADATA
jsonify_html-1.0.8.dist-info/WHEEL
jsonify_html-1.0.8.dist-info/top_level.txt
jsonify_html-1.0.8.dist-info/RECORD
