Metadata-Version: 2.1
Name: jsonify-html
Version: 1.0.8
Summary: Template-based HTML-to-JSON parser.
Home-page: https://github.com/oxdc/jsonify_html
Author: oxdc
Author-email: projaias@outlook.com
License: UNKNOWN
Platform: UNKNOWN
Requires-Dist: lxml
Requires-Dist: pytidylib
Requires-Dist: python-dateutil
Requires-Dist: django-htmlmin
Requires-Dist: cssselect
